odoo/addons/stock_production_lot_firmware_version/README.rst
odoo/addons/stock_production_lot_firmware_version/__init__.py
odoo/addons/stock_production_lot_firmware_version/__manifest__.py
odoo/addons/stock_production_lot_firmware_version/i18n/ca.po
odoo/addons/stock_production_lot_firmware_version/i18n/de.po
odoo/addons/stock_production_lot_firmware_version/i18n/es.po
odoo/addons/stock_production_lot_firmware_version/i18n/fr.po
odoo/addons/stock_production_lot_firmware_version/i18n/it.po
odoo/addons/stock_production_lot_firmware_version/i18n/stock_production_lot_firmware_version.pot
odoo/addons/stock_production_lot_firmware_version/models/__init__.py
odoo/addons/stock_production_lot_firmware_version/models/stock.py
odoo/addons/stock_production_lot_firmware_version/static/description/icon.png
odoo/addons/stock_production_lot_firmware_version/views/stock_view.xml
odoo12_addon_stock_production_lot_firmware_version-12.0.1.0.0.99.dev9.dist-info/METADATA
odoo12_addon_stock_production_lot_firmware_version-12.0.1.0.0.99.dev9.dist-info/WHEEL
odoo12_addon_stock_production_lot_firmware_version-12.0.1.0.0.99.dev9.dist-info/top_level.txt
odoo12_addon_stock_production_lot_firmware_version-12.0.1.0.0.99.dev9.dist-info/RECORD
